{
    "name": "scene",
    "objects": [
        {
            "type": "LIGHT",
            "name": "Light",
            "transform": {
                "translation": [
                    4.076245307922363,
                    1.0054539442062378,
                    5.903861999511719
                ],
                "rotation": [
                    37.261043548583984,
                    3.1637072563171387,
                    106.93630981445312
                ],
                "scaling": [
                    1.0,
                    0.9999999403953552,
                    1.0
                ]
            }
        },
        {
            "type": "CAMERA",
            "name": "Camera",
            "transform": {
                "translation": [
                    3.1399998664855957,
                    -8.55000114440918,
                    2.419999837875366
                ],
                "rotation": [
                    66.29998779296875,
                    30.0,
                    -2.3363681975752115e-06
                ],
                "scaling": [
                    1.0,
                    1.0,
                    1.0
                ]
            }
        },
        {
            "type": "MESH",
            "name": "立方体",
            "transform": {
                "translation": [
                    -2.369999885559082,
                    0.41999998688697815,
                    1.0099999904632568
                ],
                "rotation": [
                    0.0,
                    -24.5,
                    0.0
                ],
                "scaling": [
                    0.46000003814697266,
                    0.3199999928474426,
                    1.0
                ]
            },
            "children": [
                {
                    "type": "MESH",
                    "name": "Cube",
                    "transform": {
                        "translation": [
                            1.3000001907348633,
                            1.9399996995925903,
                            1.1399998664855957
                        ],
                        "rotation": [
                            -27.899999618530273,
                            -29.899993896484375,
                            1.1809427178377518e-06
                        ],
                        "scaling": [
                            2.759999990463257,
                            0.2200000137090683,
                            0.4399999678134918
                        ]
                    }
                }
            ]
        },
        {
            "type": "MESH",
            "name": "立方体.001",
            "transform": {
                "translation": [
                    2.2699999809265137,
                    5.71999979019165,
                    2.299999952316284
                ],
                "rotation": [
                    -8.584185451354642e-08,
                    38.999996185302734,
                    -22.599998474121094
                ],
                "scaling": [
                    1.0,
                    2.4699995517730713,
                    0.4700000286102295
                ]
            }
        },
        {
            "type": "MESH",
            "name": "立方体.002",
            "transform": {
                "translation": [
                    0.0,
                    6.759999752044678,
                    2.669999837875366
                ],
                "rotation": [
                    30.39999771118164,
                    -33.599998474121094,
                    -1.0800890777318273e-06
                ],
                "scaling": [
                    1.0,
                    0.5700000524520874,
                    1.0
                ]
            }
        },
        {
            "type": "MESH",
            "name": "立方体.003",
            "transform": {
                "translation": [
                    2.609999895095825,
                    1.9299999475479126,
                    0.25
                ],
                "rotation": [
                    -35.49999237060547,
                    0.0,
                    0.0
                ],
                "scaling": [
                    0.40000003576278687,
                    1.0,
                    1.0
                ]
            }
        },
        {
            "type": "MESH",
            "name": "Player",
            "transform": {
                "translation": [
                    0.0,
                    0.0,
                    0.0
                ],
                "rotation": [
                    90.00000762939453,
                    -0.0,
                    0.0
                ],
                "scaling": [
                    1.0,
                    1.0,
                    1.0
                ]
            }
        },
        {
            "type": "MESH",
            "name": "Grid",
            "transform": {
                "translation": [
                    1.850000023841858,
                    -0.12999999523162842,
                    1.1299999952316284
                ],
                "rotation": [
                    90.00000762939453,
                    -0.0,
                    0.0
                ],
                "scaling": [
                    1.0,
                    1.0,
                    1.0
                ]
            }
        },
        {
            "type": "MESH",
            "name": "Skydome",
            "transform": {
                "translation": [
                    0.0,
                    0.0,
                    0.0
                ],
                "rotation": [
                    90.00000762939453,
                    -0.0,
                    0.0
                ],
                "scaling": [
                    100.0,
                    100.0,
                    100.0
                ]
            }
        }
    ]
}